comments_generator/__init__.py
comments_generator/data/__init__.py
comments_generator/data/dataset.csv
comments_generator/generators/__init__.py
comments_generator/generators/generator.py
comments_generator-0.1.3.dist-info/licenses/LICENSE
comments_generator-0.1.3.dist-info/METADATA
comments_generator-0.1.3.dist-info/WHEEL
comments_generator-0.1.3.dist-info/top_level.txt
comments_generator-0.1.3.dist-info/RECORD
