Metadata-Version: 2.4
Name: comments_generator
Version: 0.1.3
Summary: A package for generating random comments based on category, language, and tone.
Home-page: https://github.com/yara.gafar99/comments_generator
Author: Yara Gafar
Author-email: Yara Gafar <yara.gafar99@gmail.com>
License: Apache-2.0
Requires-Python: >=3.7
License-File: LICENSE
Requires-Dist: pandas
Dynamic: author
Dynamic: home-page
Dynamic: license-file
Dynamic: requires-python
